{"temperatura": 24.88, "umidade": 40.13, "timestamp": "2025-09-27T20:04:20.702939"}
{"temperatura": 26.02, "umidade": 57.61, "timestamp": "2025-09-27T20:04:25.719748"}
{"temperatura": 28.52, "umidade": 50.81, "timestamp": "2025-09-27T20:04:30.733694"}
{"temperatura": 28.85, "umidade": 46.65, "timestamp": "2025-09-27T20:04:35.746790"}
{"temperatura": 20.95, "umidade": 52.48, "timestamp": "2025-09-27T20:04:40.761302"}
{"temperatura": 20.94, "umidade": 58.84, "timestamp": "2025-09-27T20:04:45.791898"}
{"temperatura": 23.94, "umidade": 56.87, "timestamp": "2025-09-27T20:04:50.806250"}
{"temperatura": 28.74, "umidade": 53.37, "timestamp": "2025-09-27T20:04:55.820909"}
{"temperatura": 27.44, "umidade": 51.49, "timestamp": "2025-09-27T20:05:00.835322"}
{"temperatura": 20.87, "umidade": 46.73, "timestamp": "2025-09-27T20:05:05.848233"}
{"temperatura": 24.7, "umidade": 51.9, "timestamp": "2025-09-27T20:05:10.868098"}
{"temperatura": 25.1, "umidade": 56.98, "timestamp": "2025-09-27T20:05:15.887188"}
{"temperatura": 21.69, "umidade": 51.39, "timestamp": "2025-09-27T20:05:20.906241"}
{"temperatura": 29.54, "umidade": 59.06, "timestamp": "2025-09-27T20:05:25.925018"}
{"temperatura": 27.58, "umidade": 48.81, "timestamp": "2025-09-27T20:05:30.939073"}
{"temperatura": 21.33, "umidade": 55.46, "timestamp": "2025-09-27T20:05:35.952670"}
{"temperatura": 27.84, "umidade": 45.65, "timestamp": "2025-09-27T20:05:40.959081"}
{"temperatura": 26.26, "umidade": 49.89, "timestamp": "2025-09-27T20:05:45.985172"}
{"temperatura": 22.25, "umidade": 58.28, "timestamp": "2025-09-27T20:05:51.021764"}
{"temperatura": 22.57, "umidade": 49.98, "timestamp": "2025-09-27T20:05:56.054857"}
{"temperatura": 25.42, "umidade": 41.16, "timestamp": "2025-09-27T20:06:01.067879"}
{"temperatura": 28.44, "umidade": 41.03, "timestamp": "2025-09-27T20:06:06.084673"}
